p4checkout/__init__.py
p4checkout/icon.gif
p4checkout/icon.ico
p4checkout/p4checkout.py
p4checkout-0.1.0.dist-info/METADATA
p4checkout-0.1.0.dist-info/WHEEL
p4checkout-0.1.0.dist-info/entry_points.txt
p4checkout-0.1.0.dist-info/top_level.txt
p4checkout-0.1.0.dist-info/zip-safe
p4checkout-0.1.0.dist-info/RECORD
