Metadata-Version: 2.1
Name: p4checkout
Version: 0.1.0
Summary: Standalone GUI to check out a file to a pending changelist in Perforce
Author: Dvd848
License: MIT
Project-URL: Homepage, https://github.com/Dvd848/p4checkout
Keywords: p4,perforce,gui
Classifier: Development Status :: 4 - Beta
Classifier: Environment :: Other Environment
Classifier: Intended Audience :: Developers
Classifier: License :: OSI Approved
Classifier: License :: OSI Approved :: MIT License
Classifier: Operating System :: OS Independent
Classifier: Programming Language :: Python
Classifier: Programming Language :: Python :: 3
Classifier: Programming Language :: Python :: 3 :: Only
Requires-Python: >=3.9
Requires-Dist: p4python >=2023.1.2477632
